speak/__init__.py
computerspeak-4.2.51.dist-info/License.txt
computerspeak-4.2.51.dist-info/METADATA
computerspeak-4.2.51.dist-info/WHEEL
computerspeak-4.2.51.dist-info/top_level.txt
computerspeak-4.2.51.dist-info/RECORD
