Metadata-Version: 2.1
Name: computerspeak
Version: 4.2.51
Summary: This Module Helps A User To Use Computer Audio To Make The Computer Speak AnyThing You Want
Home-page: UNKNOWN
Author: Pratyush Jha
Author-email: pratyush.jha299@gmail.com
License: License.txt
Platform: UNKNOWN
License-File: License.txt
Requires-Dist: pyttsx3
